solcx/__init__.py
solcx/exceptions.py
solcx/install.py
solcx/main.py
solcx/py.typed
solcx/version.py
solcx/wrapper.py
solcx/utils/__init__.py
solcx/utils/lock.py
py_solc_x-2.0.4.dist-info/LICENSE
py_solc_x-2.0.4.dist-info/METADATA
py_solc_x-2.0.4.dist-info/WHEEL
py_solc_x-2.0.4.dist-info/top_level.txt
py_solc_x-2.0.4.dist-info/RECORD
