Metadata-Version: 2.1
Name: py-solc-x
Version: 2.0.4
Summary: Python wrapper and version management tool for the solc Solidity compiler.
Home-page: https://github.com/ApeWorX/py-solc-x
Author: ApeWorX Ltd.
Author-email: admin@apeworx.io
License: MIT
Keywords: ethereum solidity solc
Classifier: Development Status :: 5 - Production/Stable
Classifier: Intended Audience :: Developers
Classifier: License :: OSI Approved :: MIT License
Classifier: Natural Language :: English
Classifier: Operating System :: MacOS
Classifier: Operating System :: POSIX
Classifier: Programming Language :: Python :: 3
Classifier: Programming Language :: Python :: 3.8
Classifier: Programming Language :: Python :: 3.9
Classifier: Programming Language :: Python :: 3.10
Classifier: Programming Language :: Python :: 3.11
Requires-Python: >=3.8,<4
Provides-Extra: test
Provides-Extra: lint
Provides-Extra: doc
Provides-Extra: release
Provides-Extra: dev
License-File: LICENSE
